{
    "test_labels/bzjeg.csv": [
        [
            60600,
	    64200
	],
        [
	    73200,
	    76800
	],
	[
	    465000,
	    468600
        ], 
	[
	    477000,
	    483600
	],
	[
	    520800,
	    524400
	],
	[
	    540600,
	    546600
	],
	[
	    553800,
	    558000
	],
	[
	    594000,
	    598800
	],
	[
	    652200,
	    655800
	],
        [
	    683400,
	    688200
	],
	[
	    864000,
	    869400
	],
	[
	    906600,
	    910200
	],
	[
	    1014600,
	    1018200
	],
	[
	    1046400,
	    1050000
	],
	[
	    1082400,
	    1086000
	],
	[
	    1174200,
	    1177800
	],
	[
	    1210200,
	    1215000
	],
	[
	    1284000,
	    1288200
	],
	[
	    1298400,
	    1302000
	],
	[
	    1308600,
	    1312200
	],
	[
	    1353000,
	    1356600
	],
	[
	    1467600,
	    1471200
	],
	[
	    1530000,
	    1533600
	], 
	[
	    120600,
	    124200
	],
	[
	    243600,
	    247200
	],
	[
	    287400,
	    291600
	], 
	[
	    406800,
	    411000
	],
	[
	    418200,
	    421800
	],
	[
	    435000,
	    438600
	],
	[
	    602400,
	    606000
	],
	[
	    771000,
	    774600
	],
	[
	    924000,
	    927600
	],
	[
	    928800,
	    933000
	],
	[
	    1020000,
	    1024200
	],
	[
	    1117200,
	    1120800
	],
	[
	    1140000,
	    1143600
	],
	[
	    1196400,
	    1200600
	],
	[
	    1264800,
	    1268400
	],
	[
	    1288200,
	    1291800
	], 
	[
	    1378800,
	    1382400
	],
	[
	    1504800,
	    1508400
	], 
	[
	    1518600,
	    1523400
	],
	[
	    1538400,
	    1543200
	]
    ],
    "test_labels/cuetl.csv": [
        [
	    1538400,
	    1543200
        ] 
    ],
    "test_labels/edvhp.csv": [
        [
            919200,
	    922800
	],
	[
	    959400,
	    963000
        ],
        [
            1051800,
            1056600
        ],
        [
            1080000,
            1083600
        ],
        [
            1434000,
	    1437600
        ],
        [
            778200,
            781753
        ],
        [
            900600,
            906600
        ],
 	[
            1056600,
            1060200
        ], 
        [
            1105200,
            1109400
        ],
        [
            1394400,
            1398000
        ],
        [
            1546800,
            1550400
        ]
    ],
    "test_labels/apgjp.csv": [
 	[
            34200,
            37800
        ],
        [
            249000,
            254400
        ],
        [
            257400,
            262800
        ],
        [
            336600,
            340200
        ],
        [
            382200,
            387000
        ],
        [
            586200,
            589800
        ],
        [
            996600,
            1000200
        ],
        [
            1174200,
            1177800
        ],
        [
            1252200,
            1257600
        ],
        [
            1291200,
            1294800
        ],
        [
            1386600,
            1390200
        ],
        [
            1410600,
            1414200
        ],
        [
            1539000,
            1543200
        ],
        [
            1200,
            5400
        ],
        [
            91200,
            95400
        ],
        [
            112800,
            117600
        ],
        [
            132600,
            138000
        ],
        [
            432122,
            435600
        ],
        [
            437400,
            441600
        ],
        [
            726000,
            730800
        ],
        [
            1071000,
            1076400
        ],
        [
            1087200,
            1090800
        ],
        [
            1153800,
            1158000
        ], 
        [
	    1189200,
            1192800
        ],
        [
            1201800,
            1206000
        ], 
        [
            1246200,
            1249800
        ],
        [
            1308000,
            1311813
        ],
        [
            1383000,
            1386600
        ],
        [
            1439400,
            1444800
        ],
        [
            1561200,
            1564800
        ]
    ],
    "test_labels/ceeng.csv": [
         [
            1561200,
            1564800
        ]
    ],
    "test_labels/dgqzb.csv": [
        [
            8584,
            18833
        ],
        [
            25800,
            29400
        ], 
        [
            99344,
            108330
        ],
        [
            189813,
            197379
        ],
        [
            273064,
            282319
        ],
        [
            341400,
            345000
        ],
        [
            360000,
            363600
        ],
        [
            364200,
            374677
        ],
        [
            393600,
            397200
        ], 
        [
            446400,
            450000
        ],
        [
            454718,
            465056
        ],
        [
	    499803,
            507431
        ],
        [
            606600,
            615017
        ],
        [
            633000,
            639600
        ],
        [
            662400,
            667200
        ], 
        [
            708719,
            717535
        ],
        [
            727800,
            731400
        ],
        [
            735000,
            744600
        ],
        [
            763200,
            767400
        ],
        [
            814487,
            825026
        ],
        [
            867000,
            870600
        ],
        [
            919200,
            929025
        ],
        [
            1014600,
            1018200
        ],
        [
            1023000,
            1035405
        ],
        [
            1092600,
            1097400
        ],
        [
            1105800,
            1109400
        ],
        [
            1129200,
            1132800
        ],
        [
            1133652,
            1142697
        ],
        [
            1146000,
            1149600
        ],
        [
            1164000,
            1168800
        ],
        [
            1192800,
            1197000
        ],
        [
            22200,
            25800
        ],
        [
            333000,
            336600
        ],
        [
            378000,
            381600
        ],
        [
            413400,
            417600
        ],
        [
            509400,
            513000
        ],
        [
            576600,
            581400
        ],
        [
            597000,
            600600
        ],
        [
            731400,
            735000
        ],
        [
            858000,
            862200
        ],
        [
            903000,
            906600
        ],
        [
            1061400,
            1065600
        ],
        [
            1270800,
            1276200
        ],
        [
            1487400,
            1491000
        ]
    ],
    "test_labels/frlos.csv": [
        [
            593500,
            597000
        ],
        [
            719000,
            724000
        ],
        [
            866500,
            870000
        ],
        [
            912000,
            915500
        ], 
        [
            961500,
            965000
        ], 
        [
            38703,
            42386
        ],
        [
            69000,
            73500
        ],
        [
            81500,
            84753
        ],
        [
            101552,
            104762
        ],
        [
            113000,
            118500
        ],
        [
            150000,
            153500
        ],
        [
            178565,
            181737
        ], 
        [
            187418,
            192778
        ],
        [
            200000,
            205000
        ],
        [
            217500,
            220629
        ],
        [
            227738,
            232246
        ],
        [   
            240607,
            244059
        ],
        [
            250000,
            253500
        ],
        [
            267000,
            270778
        ],
        [
            282364,
            285880
        ],
        [
            329500,
            334000
        ], 
        [
            373000,
            376500
        ],
        [
            382500,
            386000
        ],
        [
            457000,
            460500
        ], 
        [
            461000,
            466000
        ],
        [
            469762,
            473168
        ],
        [
            481993,
            487847
        ],
        [
            519507,
            526655
        ],
        [
            531728,
            534796
        ],
        [
            545000,
            548500
        ],
        [
            626500,
            631000
        ],
        [
            659745,
            663315
        ],
        [
            676475,
            679677
        ],
        [
            680289,
            683320
        ],
        [
            780500,
            784000
        ],
        [
            813837,
            817274
        ],
        [
            817275,
            821112
        ]
    ],
    "test_labels/bafgr.csv": [
        [
            343500,
            347500
        ],
        [
            406000,
            409500
        ],
        [
            677191,
            681489
        ],
        [
            735936,
            751500
        ],
        [
            813421,
            843000
        ],
        [
            849000,
            853000
        ],
        [
            883676,
            905500
        ],
        [
            932500,
            936000
        ],
        [
            960288,
            975984
        ],
        [
            987500,
            991000
        ],
        [
            1033782,
            1037499
        ],
        [
            1096000,
            1099500
        ],
        [
            1114684,
            1128870
        ],
        [
            1201820,
            1219179
        ],
        [
            1270581,
            1277466
        ],
        [
            1278500,
            1282000
        ],
        [
            1304000,
            1307500
        ],
        [
            1329889,
            1347211
        ], 
        [
            1412424,
            1415445
        ],
        [
            1416500,
            1424500
        ],
        [
            1429000,
            1433500
        ],
        [
            1485631,
            1502682
	],
        [
            1507500,
            1511000
        ],
        [
            1530500,
            1535000
        ],
        [
            22500,
            27500
	],
	[
            38423,
            67012
        ], 
        [   
            87500,
            107295
        ],
        [
            125000,
            128500
        ],
        [
            135983,
            158541
        ],
        [
            175500,
            180000
        ],
        [
            193500,
            211486
        ],
        [
            237000,
            243000
        ],
        [
            245234,
            279057
        ],
        [
            312500,
            337040
        ],
        [
            357000,
            383305
        ], 
        [
            427500,
            456201
	],
        [
            461845,
            494914
        ],
        [
            496169,
            499500
        ],
        [
            520000,
            551512
        ],
        [
            592487,
            614016
        ],
        [
            642029,
            677191
        ],
        [
            726802,
            735936
        ],
        [
            802000,
            813421
        ],
        [
            867500,
            883676
        ],
        [
            945949,
            960288
        ],
        [   
            1000000,
            1004500
        ],
        [
            1017366,
            1033782
        ],
        [
            1105368,
            1114684
        ],
        [
            1185279,
            1201820
        ],
        [
            1250608,
            1270581
        ],
        [
            1317000,
            1329889
        ],
        [
            1392547,
            1412424
        ],
        [
            1468221,
            1485631
        ], 
        [
            1559500,
            1576699
        ]
    ],
    "test_labels/cnvsw.csv": [
        [
            21067,
            29024
        ],
        [
            35400,
            39600
        ],
        [
            100800,
            105600
        ],
        [
            106800,
            110400
        ],
        [
            113505,
            122362
        ],
        [
            157200,
            160800
	],
        [
            202294,
            212058
        ],
        [
            294600,
            305376
        ], 
        [
            384995,
            394652
        ], 
        [
            475695,
            485136 
        ],
        [
            498000,
            508164
        ],
        [
            529200,
            532800
        ],
        [
            569400,
            573000
        ],
        [
            597000,
            608531
        ],
        [
            698661,
            707528
        ],
        [
            801299,
            812789
        ],
        [
            814200,
            817800
        ],
        [
            906572,
            916357
        ],
        [
            1002000,
            1012949
        ],
        [
            1022400,
            1026000
        ],
        [
            1060800,
            1068000
        ],
        [
            1093200,
            1097400
        ],
        [
            1105857,
            1116615
        ],
        [
            1167000,
            1171200
        ],
        [
            1198800,
            1203000
        ],
        [
            1207205,
            1216374
        ],
        [
            5400,
            9000
        ],
        [
            92400,
            98400
        ],
        [
            123600,
            127800
        ],
        [
            186000,
            190200
        ],
        [
            239400,
            243000
        ],
        [
            277200,
            280800
        ],
        [
            366600,
            371400
        ],
        [
            379200,
            382800
        ], 
        [
            395400,
            400800
        ],
        [
            423000,
            426600
        ],
        [
            459000,
            465600
        ],
        [
            565200,
            569400
        ], 
        [
            623400,
            628200
        ],
        [
            726000,
            730200
        ],
        [
            738000,
            745800
        ],
        [
            834600,
            838200
        ],
        [   847200,
            853800
        ],
        [
            870000,
            873600
        ],
        [
            1189800,
            1193400
        ],
        [
            1216800,
            1221000
        ],
        [
            1222800,
            1227000
        ]
    ],
    "test_labels/dkiqe.csv": [
        [
            958200,
            963600
        ],
        [ 
	    964200,
            967800
        ],
        [
            1137600,
            1141200
        ],
        [
            1193400,
            1197600
        ],
        [
            1213200,
            1216800
        ],
        [
            1417497,
            1420800
        ],
        [
            3000,
            8400
        ],
        [
            21600,
            25200
        ],
        [
            32965,
            36582
        ],
        [
            39088,
            43876
        ],
        [
            93460,
            96857
        ],
        [
            104719,
            109060
        ],
        [
            116983,
            120177
        ],
        [
            230673,
            233700
        ],
        [
            239051,
            245064
        ],
        [
            277616,
            282685
        ],
        [
            299205,
            302224
 	],
	[
	    310200,
	    318000
	],
	[
	    409297,
	    413850
	],
	[
	    454800,
	    458019
	],
	[
	    519508,
	    523132
	],
	[
	    525121,
	    528255
	],
	[
	    572400,
 	    576600
	],
	[
	    587106,
	    590414
	],
	[
	    659400,
	    663600
	],
	[
	    691166,
	    695658
	],
	[
	    698067,
	    701103
	],
	[
	    712200,
	    715800
	],
	[
	    723000,
	    726600
	],
	[
	    757800,
	    761781
	],
	[
	    817200,
	    820800
	],
	[
	    977400,
	    981000
	]
    ],
    "test_labels/oylrn.csv": [
        [
           91800,
           95400
        ],
        [
           261600,
           265800
        ], 
        [
           948600,
           954000
        ],
        [
           1189200,
           1192800
        ],
        [
           1223400,
           1227000
        ],
        [
           1341600,
           1345800
        ],
        [
           1371600,
           1376400
        ],
        [
           109800,
           113400
        ],
        [
           130200,
           133800
        ],
        [
           201600,
           205800
        ],
        [
           306000,
           310800
        ],
        [
           327600,
           331200
        ],
        [
           363000,
           366600
        ],
        [
           402000,
           405600
        ], 
        [
           414000,
           418800
        ],
        [
           442200,
           447600
        ], 
        [
           449400,
           453000
        ],
        [  468600,
           472590
        ], 
        [
           526800,
           532800
        ],
        [
           534000,
           538200
        ],
        [
           549600,
           555000
        ],
        [
           559800,
           563400
        ],
        [
           568800,
           574200
        ],
        [
           580800,
           585000
        ],
        [
           586800,
           591000
        ],
        [
           645508,
           650400
        ],
        [
           655200,
           659400
        ],
        [
           662400,
           666000
        ],
        [
           670200,
           673800
        ],
        [
           677400,
           682200
        ],
        [
           682800,
           688200
        ],
        [
           696600,
           700200
        ],
        [ 
           765600,
           769800
        ],
        [
           771000,
           780600
        ],
        [
           882000,
           885600
        ] 
    ]
}